iarahealth_stt_training/GRAPH_VERSION
iarahealth_stt_training/VERSION
iarahealth_stt_training/__init__.py
iarahealth_stt_training/deepspeech_model.py
iarahealth_stt_training/evaluate.py
iarahealth_stt_training/evaluate_export.py
iarahealth_stt_training/evaluate_flashlight.py
iarahealth_stt_training/evaluate_from_csv.py
iarahealth_stt_training/evaluate_wav2vec2am.py
iarahealth_stt_training/export.py
iarahealth_stt_training/train.py
iarahealth_stt_training/training_graph_inference.py
iarahealth_stt_training/training_graph_inference_flashlight.py
iarahealth_stt_training/transcribe.py
iarahealth_stt_training/util/__init__.py
iarahealth_stt_training/util/audio.py
iarahealth_stt_training/util/augmentations.py
iarahealth_stt_training/util/auto_input.py
iarahealth_stt_training/util/check_characters.py
iarahealth_stt_training/util/checkpoints.py
iarahealth_stt_training/util/config.py
iarahealth_stt_training/util/downloader.py
iarahealth_stt_training/util/evaluate_tools.py
iarahealth_stt_training/util/feeding.py
iarahealth_stt_training/util/gpu.py
iarahealth_stt_training/util/helpers.py
iarahealth_stt_training/util/importers.py
iarahealth_stt_training/util/io.py
iarahealth_stt_training/util/lm_optimize.py
iarahealth_stt_training/util/lm_optimize_wav2vec2am.py
iarahealth_stt_training/util/multiprocessing.py
iarahealth_stt_training/util/sample_collections.py
iarahealth_stt_training/util/stm.py
iarahealth_stt_training/util/text.py
iarahealth_stt_training-1.5.2.dist-info/LICENSE
iarahealth_stt_training-1.5.2.dist-info/METADATA
iarahealth_stt_training-1.5.2.dist-info/WHEEL
iarahealth_stt_training-1.5.2.dist-info/top_level.txt
iarahealth_stt_training-1.5.2.dist-info/RECORD
